field_health/__init__.py
field_health/test.py
field_health-1.0.0.dist-info/LICENSE
field_health-1.0.0.dist-info/METADATA
field_health-1.0.0.dist-info/WHEEL
field_health-1.0.0.dist-info/top_level.txt
field_health-1.0.0.dist-info/RECORD
