Metadata-Version: 2.1
Name: field-health
Version: 1.0.0
Summary: Field health algorithms
Home-page: https://github.com/taranisag/field-health
Author: Taranis.ag
Author-email: UNKNOWN
License: MIT
Platform: UNKNOWN
